kbmap/__init__.py
kbmap/config.py
kbmap/host.py
kbmap/kbmap.py
kbmap/key.py
kbmap/keyboard.py
kbmap/layer.py
kbmap/layout.py
kbmap/log.py
kbmap/mapper.py
kbmap/action/__init__.py
kbmap/action/action_type.py
kbmap/action/kbmap_toggle_action.py
kbmap/action/layer_mod_action.py
kbmap/action/layer_on_action.py
kbmap/action/layer_tap_action.py
kbmap/action/layer_toggle_action.py
kbmap/action/mod_key_action.py
kbmap/action/mod_tap_action.py
kbmap-1.1.0.data/scripts/kbmap
test/__init__.py
test/test_action.py
test/test_basic_mapping.py
test/test_kbmap_toggle_action.py
test/test_layer_mod_action.py
test/test_layer_on_action.py
test/test_layer_tap_action.py
test/test_layer_toggle_action.py
test/test_mod_key_action.py
test/test_mod_tap_action.py
test/util.py
kbmap-1.1.0.dist-info/LICENSE
kbmap-1.1.0.dist-info/METADATA
kbmap-1.1.0.dist-info/WHEEL
kbmap-1.1.0.dist-info/top_level.txt
kbmap-1.1.0.dist-info/RECORD
