Metadata-Version: 2.1
Name: kbmap
Version: 1.1.0
Summary: Linux keyboard mapping utility
Home-page: https://github.com/ivanjermakov/kbmap
Author: Ivan Ermakov
Author-email: ivanjermakov1@gmail.com
License: MIT
Platform: UNKNOWN
Requires-Python: >=3
Requires-Dist: evdev
Requires-Dist: click
